LICENSE
README.md
setup.cfg
setup.py
flink_sql_gateway_client/__init__.py
flink_sql_gateway_client/api_client.py
flink_sql_gateway_client/configuration.py
flink_sql_gateway_client/exceptions.py
flink_sql_gateway_client/flink_sql_client.py
flink_sql_gateway_client/flink_sql_magic.py
flink_sql_gateway_client/model_utils.py
flink_sql_gateway_client/rest.py
flink_sql_gateway_client.egg-info/PKG-INFO
flink_sql_gateway_client.egg-info/SOURCES.txt
flink_sql_gateway_client.egg-info/dependency_links.txt
flink_sql_gateway_client.egg-info/requires.txt
flink_sql_gateway_client.egg-info/top_level.txt
flink_sql_gateway_client/api/__init__.py
flink_sql_gateway_client/api/default_api.py
flink_sql_gateway_client/api/flink_sql_api.py
flink_sql_gateway_client/apis/__init__.py
flink_sql_gateway_client/model/__init__.py
flink_sql_gateway_client/model/create_session_request.py
flink_sql_gateway_client/model/create_session_response.py
flink_sql_gateway_client/model/execute_statement_request.py
flink_sql_gateway_client/model/execute_statement_response.py
flink_sql_gateway_client/model/info_response.py
flink_sql_gateway_client/model/job_status_response.py
flink_sql_gateway_client/model/result_column.py
flink_sql_gateway_client/model/result_fetch_request.py
flink_sql_gateway_client/model/result_fetch_response.py
flink_sql_gateway_client/model/result_set.py
flink_sql_gateway_client/model/session_status_response.py
flink_sql_gateway_client/models/__init__.py
test/test_create_session_request.py
test/test_create_session_response.py
test/test_default_api.py
test/test_execute_statement_request.py
test/test_execute_statement_response.py
test/test_flink_sql_api.py
test/test_info_response.py
test/test_job_status_response.py
test/test_result_column.py
test/test_result_fetch_request.py
test/test_result_fetch_response.py
test/test_result_set.py
test/test_session_status_response.py